<?xml version="1.0" encoding="UTF-8"?>
<!DOCTYPE tv SYSTEM "http://api.torrent-tv.ru/xmltv.dtd">
<tv generator-info-name="秋哥綜合" generator-info-url="https://www.tdm.com.mo/c_tv/?ch=Satellite">
<channel id="HOY國際財經"><display-name lang="zh">HOY國際財經</display-name></channel>
<channel id="HOY TV"><display-name lang="zh">HOY TV</display-name></channel>
<channel id="HOY資訊"><display-name lang="zh">HOY資訊</display-name></channel>
<programme start="20251022003000 +0800" stop="20251022013000 +0800" channel="HOY國際財經">
<title lang="zh">與君歌</title>
<desc lang="zh"> </desc>
</programme>
<programme start="20251022013000 +0800" stop="20251022020000 +0800" channel="HOY國際財經">
<title lang="zh">Bloomberg 時段</title>
<desc lang="zh"> </desc>
</programme>
<programme start="20251022020000 +0800" stop="20251022030000 +0800" channel="HOY國際財經">
<title lang="zh">Bloomberg 時段</title>
<desc lang="zh"> </desc>
</programme>
<programme start="20251022030000 +0800" stop="20251022040000 +0800" channel="HOY國際財經">
<title lang="zh">Bloomberg 時段</title>
<desc lang="zh"> </desc>
</programme>
<programme start="20251022040000 +0800" stop="20251022050000 +0800" channel="HOY國際財經">
<title lang="zh">Bloomberg 時段</title>
<desc lang="zh"> </desc>
</programme>
<programme start="20251022050000 +0800" stop="20251022060000 +0800" channel="HOY國際財經">
<title lang="zh">Bloomberg 時段</title>
<desc lang="zh"> </desc>
</programme>
<programme start="20251022060000 +0800" stop="20251022061000 +0800" channel="HOY國際財經">
<title lang="zh">Bloomberg 時段</title>
<desc lang="zh"> </desc>
</programme>
<programme start="20251022061000 +0800" stop="20251022081500 +0800" channel="HOY國際財經">
<title lang="zh">阿根廷甲組足球聯賽-聖達菲聯 對  防衛者</title>
<desc lang="zh"> </desc>
</programme>
<programme start="20251022081500 +0800" stop="20251022090000 +0800" channel="HOY國際財經">
<title lang="zh">Bloomberg 時段</title>
<desc lang="zh"> </desc>
</programme>
<programme start="20251022090000 +0800" stop="20251022093000 +0800" channel="HOY國際財經">
<title lang="zh">小恐龍可可奈 第2季</title>
<desc lang="zh"> </desc>
</programme>
<programme start="20251022093000 +0800" stop="20251022100000 +0800" channel="HOY國際財經">
<title lang="zh">Polly Pocket - 新系列 1</title>
<desc lang="zh"> </desc>
</programme>
<programme start="20251022100000 +0800" stop="20251022103000 +0800" channel="HOY國際財經">
<title lang="zh">彩虹寶寶</title>
<desc lang="zh"> </desc>
</programme>
<programme start="20251022103000 +0800" stop="20251022110000 +0800" channel="HOY國際財經">
<title lang="zh">格里蘇-小龍第1季</title>
<desc lang="zh"> </desc>
</programme>
<programme start="20251022110000 +0800" stop="20251022120000 +0800" channel="HOY國際財經">
<title lang="zh">真心假結婚</title>
<desc lang="zh"> </desc>
</programme>
<programme start="20251022120000 +0800" stop="20251022130000 +0800" channel="HOY國際財經">
<title lang="zh">與君歌</title>
<desc lang="zh"> </desc>
</programme>
<programme start="20251022130000 +0800" stop="20251022140000 +0800" channel="HOY國際財經">
<title lang="zh">Bloomberg 時段</title>
<desc lang="zh"> </desc>
</programme>
<programme start="20251022140000 +0800" stop="20251022150000 +0800" channel="HOY國際財經">
<title lang="zh">Bloomberg 時段</title>
<desc lang="zh"> </desc>
</programme>
<programme start="20251022150000 +0800" stop="20251022160000 +0800" channel="HOY國際財經">
<title lang="zh">Bloomberg 時段</title>
<desc lang="zh"> </desc>
</programme>
<programme start="20251022160000 +0800" stop="20251022163000 +0800" channel="HOY國際財經">
<title lang="zh">小恐龍可可奈 第2季</title>
<desc lang="zh"> </desc>
</programme>
<programme start="20251022163000 +0800" stop="20251022170000 +0800" channel="HOY國際財經">
<title lang="zh">格里蘇-小龍第1季</title>
<desc lang="zh"> </desc>
</programme>
<programme start="20251022170000 +0800" stop="20251022173000 +0800" channel="HOY國際財經">
<title lang="zh">彩虹寶寶</title>
<desc lang="zh"> </desc>
</programme>
<programme start="20251022173000 +0800" stop="20251022175500 +0800" channel="HOY國際財經">
<title lang="zh">Polly Pocket - 新系列 1</title>
<desc lang="zh"> </desc>
</programme>
<programme start="20251022175500 +0800" stop="20251022200000 +0800" channel="HOY國際財經">
<title lang="zh">亞洲聯賽冠軍盃精英聯賽-FC江原  對 神戶勝利船</title>
<desc lang="zh"> </desc>
</programme>
<programme start="20251022200000 +0800" stop="20251022201000 +0800" channel="HOY國際財經">
<title lang="zh">Green Touch</title>
<desc lang="zh"> </desc>
</programme>
<programme start="20251022201000 +0800" stop="20251022221500 +0800" channel="HOY國際財經">
<title lang="zh">亞洲聯賽冠軍盃二級聯賽-拉查武里  對  東方</title>
<desc lang="zh"> </desc>
</programme>
<programme start="20251022221500 +0800" stop="20251022223000 +0800" channel="HOY國際財經">
<title lang="zh">有線新聞</title>
<desc lang="zh"> </desc>
</programme>
<programme start="20251022223000 +0800" stop="20251022230000 +0800" channel="HOY國際財經">
<title lang="zh">Bloomberg 時段</title>
<desc lang="zh"> </desc>
</programme>
<programme start="20251022230000 +0800" stop="20251022231500 +0800" channel="HOY國際財經">
<title lang="zh">有線新聞</title>
<desc lang="zh"> </desc>
</programme>
<programme start="20251022231500 +0800" stop="20251022233000 +0800" channel="HOY國際財經">
<title lang="zh">Green Touch</title>
<desc lang="zh"> </desc>
</programme>
<programme start="20251022233000 +0800" stop="20251023003000 +0800" channel="HOY國際財經">
<title lang="zh">真心假結婚</title>
<desc lang="zh"> </desc>
</programme>
<programme start="20251023003000 +0800" stop="20251023013000 +0800" channel="HOY國際財經">
<title lang="zh">與君歌</title>
<desc lang="zh"> </desc>
</programme>
<programme start="20251023013000 +0800" stop="20251023020000 +0800" channel="HOY國際財經">
<title lang="zh">Bloomberg 時段</title>
<desc lang="zh"> </desc>
</programme>
<programme start="20251023020000 +0800" stop="20251023030000 +0800" channel="HOY國際財經">
<title lang="zh">Bloomberg 時段</title>
<desc lang="zh"> </desc>
</programme>
<programme start="20251023030000 +0800" stop="20251023040000 +0800" channel="HOY國際財經">
<title lang="zh">Bloomberg 時段</title>
<desc lang="zh"> </desc>
</programme>
<programme start="20251023040000 +0800" stop="20251023050000 +0800" channel="HOY國際財經">
<title lang="zh">Bloomberg 時段</title>
<desc lang="zh"> </desc>
</programme>
<programme start="20251023050000 +0800" stop="20251023060000 +0800" channel="HOY國際財經">
<title lang="zh">Bloomberg 時段</title>
<desc lang="zh"> </desc>
</programme>
<programme start="20251023060000 +0800" stop="20251023062500 +0800" channel="HOY國際財經">
<title lang="zh">Bloomberg 時段</title>
<desc lang="zh"> </desc>
</programme>
<programme start="20251023062500 +0800" stop="20251023083000 +0800" channel="HOY國際財經">
<title lang="zh">阿根廷甲組足球聯賽- 颶風隊  對  CA科爾多瓦中央</title>
<desc lang="zh"> </desc>
</programme>
<programme start="20251023083000 +0800" stop="20251023090000 +0800" channel="HOY國際財經">
<title lang="zh">Bloomberg 時段</title>
<desc lang="zh"> </desc>
</programme>
<programme start="20251023090000 +0800" stop="20251023093000 +0800" channel="HOY國際財經">
<title lang="zh">小恐龍可可奈 第2季</title>
<desc lang="zh"> </desc>
</programme>
<programme start="20251023093000 +0800" stop="20251023100000 +0800" channel="HOY國際財經">
<title lang="zh">Polly Pocket - 新系列 1</title>
<desc lang="zh"> </desc>
</programme>
<programme start="20251023100000 +0800" stop="20251023103000 +0800" channel="HOY國際財經">
<title lang="zh">彩虹寶寶</title>
<desc lang="zh"> </desc>
</programme>
<programme start="20251023103000 +0800" stop="20251023110000 +0800" channel="HOY國際財經">
<title lang="zh">格里蘇-小龍第1季</title>
<desc lang="zh"> </desc>
</programme>
<programme start="20251023110000 +0800" stop="20251023120000 +0800" channel="HOY國際財經">
<title lang="zh">真心假結婚</title>
<desc lang="zh"> </desc>
</programme>
<programme start="20251023120000 +0800" stop="20251023130000 +0800" channel="HOY國際財經">
<title lang="zh">與君歌</title>
<desc lang="zh"> </desc>
</programme>
<programme start="20251023130000 +0800" stop="20251023140000 +0800" channel="HOY國際財經">
<title lang="zh">Bloomberg 時段</title>
<desc lang="zh"> </desc>
</programme>
<programme start="20251023140000 +0800" stop="20251023150000 +0800" channel="HOY國際財經">
<title lang="zh">Bloomberg 時段</title>
<desc lang="zh"> </desc>
</programme>
<programme start="20251023150000 +0800" stop="20251023153000 +0800" channel="HOY國際財經">
<title lang="zh">Bloomberg 時段</title>
<desc lang="zh"> </desc>
</programme>
<programme start="20251023153000 +0800" stop="20251023160000 +0800" channel="HOY國際財經">
<title lang="zh">阿聯酋職業足球聯賽雜誌</title>
<desc lang="zh"> </desc>
</programme>
<programme start="20251023160000 +0800" stop="20251023163000 +0800" channel="HOY國際財經">
<title lang="zh">小恐龍可可奈 第2季</title>
<desc lang="zh"> </desc>
</programme>
<programme start="20251023163000 +0800" stop="20251023170000 +0800" channel="HOY國際財經">
<title lang="zh">格里蘇-小龍第1季</title>
<desc lang="zh"> </desc>
</programme>
<programme start="20251023170000 +0800" stop="20251023173000 +0800" channel="HOY國際財經">
<title lang="zh">彩虹寶寶</title>
<desc lang="zh"> </desc>
</programme>
<programme start="20251023173000 +0800" stop="20251023175500 +0800" channel="HOY國際財經">
<title lang="zh">Polly Pocket - 新系列 1</title>
<desc lang="zh"> </desc>
</programme>
<programme start="20251023175500 +0800" stop="20251023200000 +0800" channel="HOY國際財經">
<title lang="zh">亞洲聯賽冠軍盃二級聯賽-大埔  對  FC北京</title>
<desc lang="zh"> </desc>
</programme>
<programme start="20251023200000 +0800" stop="20251023201000 +0800" channel="HOY國際財經">
<title lang="zh">Green Touch</title>
<desc lang="zh"> </desc>
</programme>
<programme start="20251023201000 +0800" stop="20251023221500 +0800" channel="HOY國際財經">
<title lang="zh">亞洲聯賽冠軍盃二級聯賽-曼谷聯  對  獅城水手</title>
<desc lang="zh"> </desc>
</programme>
<programme start="20251023221500 +0800" stop="20251023223000 +0800" channel="HOY國際財經">
<title lang="zh">有線新聞</title>
<desc lang="zh"> </desc>
</programme>
<programme start="20251023223000 +0800" stop="20251023230000 +0800" channel="HOY國際財經">
<title lang="zh">Bloomberg 時段</title>
<desc lang="zh"> </desc>
</programme>
<programme start="20251023230000 +0800" stop="20251023231500 +0800" channel="HOY國際財經">
<title lang="zh">有線新聞</title>
<desc lang="zh"> </desc>
</programme>
<programme start="20251023231500 +0800" stop="20251023233000 +0800" channel="HOY國際財經">
<title lang="zh">Green Touch</title>
<desc lang="zh"> </desc>
</programme>
<programme start="20251023233000 +0800" stop="20251024003000 +0800" channel="HOY國際財經">
<title lang="zh">真心假結婚</title>
<desc lang="zh"> </desc>
</programme>
<programme start="20251022001500 +0800" stop="20251022004500 +0800" channel="HOY TV">
<title lang="zh">追素解決師</title>
<desc lang="zh"> </desc>
</programme>
<programme start="20251022004500 +0800" stop="20251022010000 +0800" channel="HOY TV">
<title lang="zh">娛樂頭條 E-news Headline</title>
<desc lang="zh"> </desc>
</programme>
<programme start="20251022010000 +0800" stop="20251022030000 +0800" channel="HOY TV">
<title lang="zh">HOY 動音樂</title>
<desc lang="zh"> </desc>
</programme>
<programme start="20251022030000 +0800" stop="20251022060000 +0800" channel="HOY TV">
<title lang="zh">魚樂無限</title>
<desc lang="zh"> </desc>
</programme>
<programme start="20251022060000 +0800" stop="20251022070000 +0800" channel="HOY TV">
<title lang="zh">幸福大家姐</title>
<desc lang="zh"> </desc>
</programme>
<programme start="20251022070000 +0800" stop="20251022080000 +0800" channel="HOY TV">
<title lang="zh">凌雲志</title>
<desc lang="zh"> </desc>
</programme>
<programme start="20251022080000 +0800" stop="20251022085500 +0800" channel="HOY TV">
<title lang="zh">會長的愛</title>
<desc lang="zh"> </desc>
</programme>
<programme start="20251022085500 +0800" stop="20251022090000 +0800" channel="HOY TV">
<title lang="zh">防災應急18識</title>
<desc lang="zh"> </desc>
</programme>
<programme start="20251022090000 +0800" stop="20251022093000 +0800" channel="HOY TV">
<title lang="zh">開飯啦</title>
<desc lang="zh"> </desc>
</programme>
<programme start="20251022093000 +0800" stop="20251022100000 +0800" channel="HOY TV">
<title lang="zh">馬田點食記 台灣篇</title>
<desc lang="zh"> </desc>
</programme>
<programme start="20251022100000 +0800" stop="20251022102500 +0800" channel="HOY TV">
<title lang="zh">地膽帶路日本遊</title>
<desc lang="zh"> </desc>
</programme>
<programme start="20251022102500 +0800" stop="20251022103000 +0800" channel="HOY TV">
<title lang="zh">全運倒數</title>
<desc lang="zh"> </desc>
</programme>
<programme start="20251022103000 +0800" stop="20251022112500 +0800" channel="HOY TV">
<title lang="zh">灰姑娘遊戲</title>
<desc lang="zh"> </desc>
</programme>
<programme start="20251022112500 +0800" stop="20251022113000 +0800" channel="HOY TV">
<title lang="zh">全運倒數</title>
<desc lang="zh"> </desc>
</programme>
<programme start="20251022113000 +0800" stop="20251022122500 +0800" channel="HOY TV">
<title lang="zh">幸福大家姐</title>
<desc lang="zh"> </desc>
</programme>
<programme start="20251022122500 +0800" stop="20251022123000 +0800" channel="HOY TV">
<title lang="zh">全運倒數</title>
<desc lang="zh"> </desc>
</programme>
<programme start="20251022123000 +0800" stop="20251022130000 +0800" channel="HOY TV">
<title lang="zh">午間新聞</title>
<desc lang="zh"> </desc>
</programme>
<programme start="20251022130000 +0800" stop="20251022133000 +0800" channel="HOY TV">
<title lang="zh">一線搜查</title>
<desc lang="zh"> </desc>
</programme>
<programme start="20251022133000 +0800" stop="20251022140000 +0800" channel="HOY TV">
<title lang="zh">東方表行 Take Your Time 特約 : 一個人鐵道行 4</title>
<desc lang="zh"> </desc>
</programme>
<programme start="20251022140000 +0800" stop="20251022143000 +0800" channel="HOY TV">
<title lang="zh">健康關注組</title>
<desc lang="zh"> </desc>
</programme>
<programme start="20251022143000 +0800" stop="20251022150000 +0800" channel="HOY TV">
<title lang="zh">南滋北味</title>
<desc lang="zh"> </desc>
</programme>
<programme start="20251022150000 +0800" stop="20251022152500 +0800" channel="HOY TV">
<title lang="zh">黑白大廚滋味行</title>
<desc lang="zh"> </desc>
</programme>
<programme start="20251022152500 +0800" stop="20251022153000 +0800" channel="HOY TV">
<title lang="zh">全運倒數</title>
<desc lang="zh"> </desc>
</programme>
<programme start="20251022153000 +0800" stop="20251022155500 +0800" channel="HOY TV">
<title lang="zh">君九齡</title>
<desc lang="zh"> </desc>
</programme>
<programme start="20251022155500 +0800" stop="20251022160000 +0800" channel="HOY TV">
<title lang="zh">全運倒數</title>
<desc lang="zh"> </desc>
</programme>
<programme start="20251022160000 +0800" stop="20251022163000 +0800" channel="HOY TV">
<title lang="zh">柚木家的四兄弟</title>
<desc lang="zh"> </desc>
</programme>
<programme start="20251022163000 +0800" stop="20251022170000 +0800" channel="HOY TV">
<title lang="zh">龍族拼圖X</title>
<desc lang="zh"> </desc>
</programme>
<programme start="20251022170000 +0800" stop="20251022173000 +0800" channel="HOY TV">
<title lang="zh">地底小靈精</title>
<desc lang="zh"> </desc>
</programme>
<programme start="20251022173000 +0800" stop="20251022175500 +0800" channel="HOY TV">
<title lang="zh">汪汪隊立大功</title>
<desc lang="zh"> </desc>
</programme>
<programme start="20251022175500 +0800" stop="20251022180000 +0800" channel="HOY TV">
<title lang="zh">全運倒數</title>
<desc lang="zh"> </desc>
</programme>
<programme start="20251022180000 +0800" stop="20251022183000 +0800" channel="HOY TV">
<title lang="zh">追素解決師</title>
<desc lang="zh"> </desc>
</programme>
<programme start="20251022183000 +0800" stop="20251022190000 +0800" channel="HOY TV">
<title lang="zh">地膽帶路日本遊</title>
<desc lang="zh"> </desc>
</programme>
<programme start="20251022190000 +0800" stop="20251022194500 +0800" channel="HOY TV">
<title lang="zh">7點直播室</title>
<desc lang="zh"> </desc>
</programme>
<programme start="20251022194500 +0800" stop="20251022195000 +0800" channel="HOY TV">
<title lang="zh">28Hse特約 : 每日樓市</title>
<desc lang="zh"> </desc>
</programme>
<programme start="20251022195000 +0800" stop="20251022200000 +0800" channel="HOY TV">
<title lang="zh">防災應急18識</title>
<desc lang="zh"> </desc>
</programme>
<programme start="20251022200000 +0800" stop="20251022202500 +0800" channel="HOY TV">
<title lang="zh">一線搜查</title>
<desc lang="zh"> </desc>
</programme>
<programme start="20251022202500 +0800" stop="20251022203000 +0800" channel="HOY TV">
<title lang="zh">全運倒數</title>
<desc lang="zh"> </desc>
</programme>
<programme start="20251022203000 +0800" stop="20251022210000 +0800" channel="HOY TV">
<title lang="zh">東方表行 Take Your Time 特約 : 一個人鐵道行 4</title>
<desc lang="zh"> </desc>
</programme>
<programme start="20251022210000 +0800" stop="20251022210500 +0800" channel="HOY TV">
<title lang="zh">郭Sir! 學警A班到齊!</title>
<desc lang="zh"> </desc>
</programme>
<programme start="20251022210500 +0800" stop="20251022213000 +0800" channel="HOY TV">
<title lang="zh">健康關注組</title>
<desc lang="zh"> </desc>
</programme>
<programme start="20251022213000 +0800" stop="20251022215500 +0800" channel="HOY TV">
<title lang="zh">南滋北味</title>
<desc lang="zh"> </desc>
</programme>
<programme start="20251022215500 +0800" stop="20251022220000 +0800" channel="HOY TV">
<title lang="zh">全運倒數</title>
<desc lang="zh"> </desc>
</programme>
<programme start="20251022220000 +0800" stop="20251022230000 +0800" channel="HOY TV">
<title lang="zh">灰姑娘遊戲</title>
<desc lang="zh"> </desc>
</programme>
<programme start="20251022230000 +0800" stop="20251022233000 +0800" channel="HOY TV">
<title lang="zh">有線新聞</title>
<desc lang="zh"> </desc>
</programme>
<programme start="20251022233000 +0800" stop="20251022234500 +0800" channel="HOY TV">
<title lang="zh">娛樂頭條 E-news Headline</title>
<desc lang="zh"> </desc>
</programme>
<programme start="20251022234500 +0800" stop="20251023001500 +0800" channel="HOY TV">
<title lang="zh">開飯啦</title>
<desc lang="zh"> </desc>
</programme>
<programme start="20251023001500 +0800" stop="20251023004500 +0800" channel="HOY TV">
<title lang="zh">追素解決師</title>
<desc lang="zh"> </desc>
</programme>
<programme start="20251023004500 +0800" stop="20251023010000 +0800" channel="HOY TV">
<title lang="zh">娛樂頭條 E-news Headline</title>
<desc lang="zh"> </desc>
</programme>
<programme start="20251023010000 +0800" stop="20251023030000 +0800" channel="HOY TV">
<title lang="zh">HOY 動音樂</title>
<desc lang="zh"> </desc>
</programme>
<programme start="20251023030000 +0800" stop="20251023060000 +0800" channel="HOY TV">
<title lang="zh">魚樂無限</title>
<desc lang="zh"> </desc>
</programme>
<programme start="20251023060000 +0800" stop="20251023070000 +0800" channel="HOY TV">
<title lang="zh">幸福大家姐</title>
<desc lang="zh"> </desc>
</programme>
<programme start="20251023070000 +0800" stop="20251023080000 +0800" channel="HOY TV">
<title lang="zh">凌雲志</title>
<desc lang="zh"> </desc>
</programme>
<programme start="20251023080000 +0800" stop="20251023085500 +0800" channel="HOY TV">
<title lang="zh">會長的愛</title>
<desc lang="zh"> </desc>
</programme>
<programme start="20251023085500 +0800" stop="20251023090000 +0800" channel="HOY TV">
<title lang="zh">防災應急18識</title>
<desc lang="zh"> </desc>
</programme>
<programme start="20251023090000 +0800" stop="20251023093000 +0800" channel="HOY TV">
<title lang="zh">開飯啦</title>
<desc lang="zh"> </desc>
</programme>
<programme start="20251023093000 +0800" stop="20251023100000 +0800" channel="HOY TV">
<title lang="zh">馬田點食記 台灣篇</title>
<desc lang="zh"> </desc>
</programme>
<programme start="20251023100000 +0800" stop="20251023102500 +0800" channel="HOY TV">
<title lang="zh">地膽帶路日本遊</title>
<desc lang="zh"> </desc>
</programme>
<programme start="20251023102500 +0800" stop="20251023103000 +0800" channel="HOY TV">
<title lang="zh">全運倒數</title>
<desc lang="zh"> </desc>
</programme>
<programme start="20251023103000 +0800" stop="20251023112500 +0800" channel="HOY TV">
<title lang="zh">灰姑娘遊戲</title>
<desc lang="zh"> </desc>
</programme>
<programme start="20251023112500 +0800" stop="20251023113000 +0800" channel="HOY TV">
<title lang="zh">全運倒數</title>
<desc lang="zh"> </desc>
</programme>
<programme start="20251023113000 +0800" stop="20251023122500 +0800" channel="HOY TV">
<title lang="zh">幸福大家姐</title>
<desc lang="zh"> </desc>
</programme>
<programme start="20251023122500 +0800" stop="20251023123000 +0800" channel="HOY TV">
<title lang="zh">全運倒數</title>
<desc lang="zh"> </desc>
</programme>
<programme start="20251023123000 +0800" stop="20251023130000 +0800" channel="HOY TV">
<title lang="zh">午間新聞</title>
<desc lang="zh"> </desc>
</programme>
<programme start="20251023130000 +0800" stop="20251023133000 +0800" channel="HOY TV">
<title lang="zh">一線搜查</title>
<desc lang="zh"> </desc>
</programme>
<programme start="20251023133000 +0800" stop="20251023140000 +0800" channel="HOY TV">
<title lang="zh">東方表行 Take Your Time 特約 : 一個人鐵道行 4</title>
<desc lang="zh"> </desc>
</programme>
<programme start="20251023140000 +0800" stop="20251023143000 +0800" channel="HOY TV">
<title lang="zh">健康關注組</title>
<desc lang="zh"> </desc>
</programme>
<programme start="20251023143000 +0800" stop="20251023150000 +0800" channel="HOY TV">
<title lang="zh">南滋北味</title>
<desc lang="zh"> </desc>
</programme>
<programme start="20251023150000 +0800" stop="20251023152500 +0800" channel="HOY TV">
<title lang="zh">Lolly Lolly寵物拯救隊</title>
<desc lang="zh"> </desc>
</programme>
<programme start="20251023152500 +0800" stop="20251023153000 +0800" channel="HOY TV">
<title lang="zh">全運倒數</title>
<desc lang="zh"> </desc>
</programme>
<programme start="20251023153000 +0800" stop="20251023155500 +0800" channel="HOY TV">
<title lang="zh">君九齡</title>
<desc lang="zh"> </desc>
</programme>
<programme start="20251023155500 +0800" stop="20251023160000 +0800" channel="HOY TV">
<title lang="zh">全運倒數</title>
<desc lang="zh"> </desc>
</programme>
<programme start="20251023160000 +0800" stop="20251023163000 +0800" channel="HOY TV">
<title lang="zh">柚木家的四兄弟</title>
<desc lang="zh"> </desc>
</programme>
<programme start="20251023163000 +0800" stop="20251023170000 +0800" channel="HOY TV">
<title lang="zh">龍族拼圖X</title>
<desc lang="zh"> </desc>
</programme>
<programme start="20251023170000 +0800" stop="20251023173000 +0800" channel="HOY TV">
<title lang="zh">地底小靈精</title>
<desc lang="zh"> </desc>
</programme>
<programme start="20251023173000 +0800" stop="20251023175500 +0800" channel="HOY TV">
<title lang="zh">汪汪隊立大功</title>
<desc lang="zh"> </desc>
</programme>
<programme start="20251023175500 +0800" stop="20251023180000 +0800" channel="HOY TV">
<title lang="zh">全運倒數</title>
<desc lang="zh"> </desc>
</programme>
<programme start="20251023180000 +0800" stop="20251023183000 +0800" channel="HOY TV">
<title lang="zh">追素解決師</title>
<desc lang="zh"> </desc>
</programme>
<programme start="20251023183000 +0800" stop="20251023190000 +0800" channel="HOY TV">
<title lang="zh">地膽帶路日本遊</title>
<desc lang="zh"> </desc>
</programme>
<programme start="20251023190000 +0800" stop="20251023195000 +0800" channel="HOY TV">
<title lang="zh">7點直播室</title>
<desc lang="zh"> </desc>
</programme>
<programme start="20251023195000 +0800" stop="20251023200000 +0800" channel="HOY TV">
<title lang="zh">28Hse特約 : 每日樓市</title>
<desc lang="zh"> </desc>
</programme>
<programme start="20251023200000 +0800" stop="20251023202500 +0800" channel="HOY TV">
<title lang="zh">一線搜查</title>
<desc lang="zh"> </desc>
</programme>
<programme start="20251023202500 +0800" stop="20251023203000 +0800" channel="HOY TV">
<title lang="zh">全運倒數</title>
<desc lang="zh"> </desc>
</programme>
<programme start="20251023203000 +0800" stop="20251023210000 +0800" channel="HOY TV">
<title lang="zh">東方表行 Take Your Time 特約 : 一個人鐵道行 4</title>
<desc lang="zh"> </desc>
</programme>
<programme start="20251023210000 +0800" stop="20251023210500 +0800" channel="HOY TV">
<title lang="zh">郭Sir! 學警A班到齊!</title>
<desc lang="zh"> </desc>
</programme>
<programme start="20251023210500 +0800" stop="20251023213000 +0800" channel="HOY TV">
<title lang="zh">健康關注組</title>
<desc lang="zh"> </desc>
</programme>
<programme start="20251023213000 +0800" stop="20251023215500 +0800" channel="HOY TV">
<title lang="zh">南滋北味</title>
<desc lang="zh"> </desc>
</programme>
<programme start="20251023215500 +0800" stop="20251023220000 +0800" channel="HOY TV">
<title lang="zh">全運倒數</title>
<desc lang="zh"> </desc>
</programme>
<programme start="20251023220000 +0800" stop="20251023230000 +0800" channel="HOY TV">
<title lang="zh">灰姑娘遊戲</title>
<desc lang="zh"> </desc>
</programme>
<programme start="20251023230000 +0800" stop="20251023233000 +0800" channel="HOY TV">
<title lang="zh">有線新聞</title>
<desc lang="zh"> </desc>
</programme>
<programme start="20251023233000 +0800" stop="20251023234500 +0800" channel="HOY TV">
<title lang="zh">娛樂頭條 E-news Headline</title>
<desc lang="zh"> </desc>
</programme>
<programme start="20251023234500 +0800" stop="20251024001500 +0800" channel="HOY TV">
<title lang="zh">開飯啦</title>
<desc lang="zh"> </desc>
</programme>
<programme start="20251022000000 +0800" stop="20251022003000 +0800" channel="HOY資訊">
<title lang="zh">有線新聞</title>
<desc lang="zh"> </desc>
</programme>
<programme start="20251022003000 +0800" stop="20251022010000 +0800" channel="HOY資訊">
<title lang="zh">有線新聞</title>
<desc lang="zh"> </desc>
</programme>
<programme start="20251022010000 +0800" stop="20251022013000 +0800" channel="HOY資訊">
<title lang="zh">有線新聞</title>
<desc lang="zh"> </desc>
</programme>
<programme start="20251022013000 +0800" stop="20251022020000 +0800" channel="HOY資訊">
<title lang="zh">有線新聞</title>
<desc lang="zh"> </desc>
</programme>
<programme start="20251022020000 +0800" stop="20251022023000 +0800" channel="HOY資訊">
<title lang="zh">有線新聞</title>
<desc lang="zh"> </desc>
</programme>
<programme start="20251022023000 +0800" stop="20251022030000 +0800" channel="HOY資訊">
<title lang="zh">有線新聞</title>
<desc lang="zh"> </desc>
</programme>
<programme start="20251022030000 +0800" stop="20251022033000 +0800" channel="HOY資訊">
<title lang="zh">有線新聞</title>
<desc lang="zh"> </desc>
</programme>
<programme start="20251022033000 +0800" stop="20251022040000 +0800" channel="HOY資訊">
<title lang="zh">有線新聞</title>
<desc lang="zh"> </desc>
</programme>
<programme start="20251022040000 +0800" stop="20251022043000 +0800" channel="HOY資訊">
<title lang="zh">有線新聞</title>
<desc lang="zh"> </desc>
</programme>
<programme start="20251022043000 +0800" stop="20251022050000 +0800" channel="HOY資訊">
<title lang="zh">有線新聞</title>
<desc lang="zh"> </desc>
</programme>
<programme start="20251022050000 +0800" stop="20251022053000 +0800" channel="HOY資訊">
<title lang="zh">有線新聞</title>
<desc lang="zh"> </desc>
</programme>
<programme start="20251022053000 +0800" stop="20251022060000 +0800" channel="HOY資訊">
<title lang="zh">有線新聞</title>
<desc lang="zh"> </desc>
</programme>
<programme start="20251022060000 +0800" stop="20251022063000 +0800" channel="HOY資訊">
<title lang="zh">有線新聞</title>
<desc lang="zh"> </desc>
</programme>
<programme start="20251022063000 +0800" stop="20251022070000 +0800" channel="HOY資訊">
<title lang="zh">有線新聞</title>
<desc lang="zh"> </desc>
</programme>
<programme start="20251022070000 +0800" stop="20251022073000 +0800" channel="HOY資訊">
<title lang="zh">Cable 早晨</title>
<desc lang="zh"> </desc>
</programme>
<programme start="20251022073000 +0800" stop="20251022075800 +0800" channel="HOY資訊">
<title lang="zh">Cable 早晨</title>
<desc lang="zh"> </desc>
</programme>
<programme start="20251022075800 +0800" stop="20251022080000 +0800" channel="HOY資訊">
<title lang="zh">全運倒數</title>
<desc lang="zh"> </desc>
</programme>
<programme start="20251022080000 +0800" stop="20251022083000 +0800" channel="HOY資訊">
<title lang="zh">Cable 早晨</title>
<desc lang="zh"> </desc>
</programme>
<programme start="20251022083000 +0800" stop="20251022085800 +0800" channel="HOY資訊">
<title lang="zh">Cable 早晨</title>
<desc lang="zh"> </desc>
</programme>
<programme start="20251022085800 +0800" stop="20251022090000 +0800" channel="HOY資訊">
<title lang="zh">全運倒數</title>
<desc lang="zh"> </desc>
</programme>
<programme start="20251022090000 +0800" stop="20251022100000 +0800" channel="HOY資訊">
<title lang="zh">股市直播室</title>
<desc lang="zh"> </desc>
</programme>
<programme start="20251022100000 +0800" stop="20251022103000 +0800" channel="HOY資訊">
<title lang="zh">有線新聞</title>
<desc lang="zh"> </desc>
</programme>
<programme start="20251022103000 +0800" stop="20251022110000 +0800" channel="HOY資訊">
<title lang="zh">有線新聞</title>
<desc lang="zh"> </desc>
</programme>
<programme start="20251022110000 +0800" stop="20251022113000 +0800" channel="HOY資訊">
<title lang="zh">有線新聞</title>
<desc lang="zh"> </desc>
</programme>
<programme start="20251022113000 +0800" stop="20251022120000 +0800" channel="HOY資訊">
<title lang="zh">智‧創未來</title>
<desc lang="zh"> </desc>
</programme>
<programme start="20251022120000 +0800" stop="20251022123000 +0800" channel="HOY資訊">
<title lang="zh">有線新聞</title>
<desc lang="zh"> </desc>
</programme>
<programme start="20251022123000 +0800" stop="20251022130000 +0800" channel="HOY資訊">
<title lang="zh">午間新聞</title>
<desc lang="zh"> </desc>
</programme>
<programme start="20251022130000 +0800" stop="20251022132800 +0800" channel="HOY資訊">
<title lang="zh">有線新聞</title>
<desc lang="zh"> </desc>
</programme>
<programme start="20251022132800 +0800" stop="20251022133000 +0800" channel="HOY資訊">
<title lang="zh">全運倒數</title>
<desc lang="zh"> </desc>
</programme>
<programme start="20251022133000 +0800" stop="20251022140000 +0800" channel="HOY資訊">
<title lang="zh">28Hse特約：家家有求</title>
<desc lang="zh"> </desc>
</programme>
<programme start="20251022140000 +0800" stop="20251022142800 +0800" channel="HOY資訊">
<title lang="zh">有線新聞</title>
<desc lang="zh"> </desc>
</programme>
<programme start="20251022142800 +0800" stop="20251022143000 +0800" channel="HOY資訊">
<title lang="zh">全運倒數</title>
<desc lang="zh"> </desc>
</programme>
<programme start="20251022143000 +0800" stop="20251022150000 +0800" channel="HOY資訊">
<title lang="zh">有線新聞</title>
<desc lang="zh"> </desc>
</programme>
<programme start="20251022150000 +0800" stop="20251022152800 +0800" channel="HOY資訊">
<title lang="zh">有線新聞</title>
<desc lang="zh"> </desc>
</programme>
<programme start="20251022152800 +0800" stop="20251022153000 +0800" channel="HOY資訊">
<title lang="zh">全運倒數</title>
<desc lang="zh"> </desc>
</programme>
<programme start="20251022153000 +0800" stop="20251022160000 +0800" channel="HOY資訊">
<title lang="zh">有線新聞</title>
<desc lang="zh"> </desc>
</programme>
<programme start="20251022160000 +0800" stop="20251022163000 +0800" channel="HOY資訊">
<title lang="zh">股市直播室</title>
<desc lang="zh"> </desc>
</programme>
<programme start="20251022163000 +0800" stop="20251022170000 +0800" channel="HOY資訊">
<title lang="zh">有線新聞</title>
<desc lang="zh"> </desc>
</programme>
<programme start="20251022170000 +0800" stop="20251022173000 +0800" channel="HOY資訊">
<title lang="zh">有線新聞</title>
<desc lang="zh"> </desc>
</programme>
<programme start="20251022173000 +0800" stop="20251022175800 +0800" channel="HOY資訊">
<title lang="zh">股市直播室</title>
<desc lang="zh"> </desc>
</programme>
<programme start="20251022175800 +0800" stop="20251022180000 +0800" channel="HOY資訊">
<title lang="zh">全運倒數</title>
<desc lang="zh"> </desc>
</programme>
<programme start="20251022180000 +0800" stop="20251022183000 +0800" channel="HOY資訊">
<title lang="zh">手語新聞報道</title>
<desc lang="zh"> </desc>
</programme>
<programme start="20251022183000 +0800" stop="20251022184500 +0800" channel="HOY資訊">
<title lang="zh">六點半新聞報道</title>
<desc lang="zh"> </desc>
</programme>
<programme start="20251022184500 +0800" stop="20251022190000 +0800" channel="HOY資訊">
<title lang="zh">焦點財經</title>
<desc lang="zh"> </desc>
</programme>
<programme start="20251022190000 +0800" stop="20251022194500 +0800" channel="HOY資訊">
<title lang="zh">7點直播室</title>
<desc lang="zh"> </desc>
</programme>
<programme start="20251022194500 +0800" stop="20251022195000 +0800" channel="HOY資訊">
<title lang="zh">28Hse特約 : 每日樓市</title>
<desc lang="zh"> </desc>
</programme>
<programme start="20251022195000 +0800" stop="20251022200000 +0800" channel="HOY資訊">
<title lang="zh">防災應急18識</title>
<desc lang="zh"> </desc>
</programme>
<programme start="20251022200000 +0800" stop="20251022203000 +0800" channel="HOY資訊">
<title lang="zh">國際最前線</title>
<desc lang="zh"> </desc>
</programme>
<programme start="20251022203000 +0800" stop="20251022205800 +0800" channel="HOY資訊">
<title lang="zh">一線搜查</title>
<desc lang="zh"> </desc>
</programme>
<programme start="20251022205800 +0800" stop="20251022210000 +0800" channel="HOY資訊">
<title lang="zh">全運倒數</title>
<desc lang="zh"> </desc>
</programme>
<programme start="20251022210000 +0800" stop="20251022214500 +0800" channel="HOY資訊">
<title lang="zh">晚間直播室</title>
<desc lang="zh"> </desc>
</programme>
<programme start="20251022214500 +0800" stop="20251022220000 +0800" channel="HOY資訊">
<title lang="zh">焦點財經及28Hse特約:每日樓市</title>
<desc lang="zh"> </desc>
</programme>
<programme start="20251022220000 +0800" stop="20251022223000 +0800" channel="HOY資訊">
<title lang="zh">家國天下</title>
<desc lang="zh"> </desc>
</programme>
<programme start="20251022223000 +0800" stop="20251022225800 +0800" channel="HOY資訊">
<title lang="zh">一線搜查</title>
<desc lang="zh"> </desc>
</programme>
<programme start="20251022225800 +0800" stop="20251022230000 +0800" channel="HOY資訊">
<title lang="zh">全運倒數</title>
<desc lang="zh"> </desc>
</programme>
<programme start="20251022230000 +0800" stop="20251022233000 +0800" channel="HOY資訊">
<title lang="zh">有線新聞</title>
<desc lang="zh"> </desc>
</programme>
<programme start="20251022233000 +0800" stop="20251023000000 +0800" channel="HOY資訊">
<title lang="zh">有線新聞</title>
<desc lang="zh"> </desc>
</programme>
<programme start="20251023000000 +0800" stop="20251023003000 +0800" channel="HOY資訊">
<title lang="zh">有線新聞</title>
<desc lang="zh"> </desc>
</programme>
<programme start="20251023003000 +0800" stop="20251023010000 +0800" channel="HOY資訊">
<title lang="zh">有線新聞</title>
<desc lang="zh"> </desc>
</programme>
<programme start="20251023010000 +0800" stop="20251023013000 +0800" channel="HOY資訊">
<title lang="zh">有線新聞</title>
<desc lang="zh"> </desc>
</programme>
<programme start="20251023013000 +0800" stop="20251023020000 +0800" channel="HOY資訊">
<title lang="zh">有線新聞</title>
<desc lang="zh"> </desc>
</programme>
<programme start="20251023020000 +0800" stop="20251023023000 +0800" channel="HOY資訊">
<title lang="zh">有線新聞</title>
<desc lang="zh"> </desc>
</programme>
<programme start="20251023023000 +0800" stop="20251023030000 +0800" channel="HOY資訊">
<title lang="zh">有線新聞</title>
<desc lang="zh"> </desc>
</programme>
<programme start="20251023030000 +0800" stop="20251023033000 +0800" channel="HOY資訊">
<title lang="zh">有線新聞</title>
<desc lang="zh"> </desc>
</programme>
<programme start="20251023033000 +0800" stop="20251023040000 +0800" channel="HOY資訊">
<title lang="zh">有線新聞</title>
<desc lang="zh"> </desc>
</programme>
<programme start="20251023040000 +0800" stop="20251023043000 +0800" channel="HOY資訊">
<title lang="zh">有線新聞</title>
<desc lang="zh"> </desc>
</programme>
<programme start="20251023043000 +0800" stop="20251023050000 +0800" channel="HOY資訊">
<title lang="zh">有線新聞</title>
<desc lang="zh"> </desc>
</programme>
<programme start="20251023050000 +0800" stop="20251023053000 +0800" channel="HOY資訊">
<title lang="zh">有線新聞</title>
<desc lang="zh"> </desc>
</programme>
<programme start="20251023053000 +0800" stop="20251023060000 +0800" channel="HOY資訊">
<title lang="zh">有線新聞</title>
<desc lang="zh"> </desc>
</programme>
<programme start="20251023060000 +0800" stop="20251023063000 +0800" channel="HOY資訊">
<title lang="zh">有線新聞</title>
<desc lang="zh"> </desc>
</programme>
<programme start="20251023063000 +0800" stop="20251023070000 +0800" channel="HOY資訊">
<title lang="zh">有線新聞</title>
<desc lang="zh"> </desc>
</programme>
<programme start="20251023070000 +0800" stop="20251023072500 +0800" channel="HOY資訊">
<title lang="zh">Cable 早晨</title>
<desc lang="zh"> </desc>
</programme>
<programme start="20251023072500 +0800" stop="20251023073000 +0800" channel="HOY資訊">
<title lang="zh">House730 特約 : 樓市導航</title>
<desc lang="zh"> </desc>
</programme>
<programme start="20251023073000 +0800" stop="20251023075500 +0800" channel="HOY資訊">
<title lang="zh">Cable 早晨</title>
<desc lang="zh"> </desc>
</programme>
<programme start="20251023075500 +0800" stop="20251023075800 +0800" channel="HOY資訊">
<title lang="zh">House730 特約 : 樓市導航</title>
<desc lang="zh"> </desc>
</programme>
<programme start="20251023075800 +0800" stop="20251023080000 +0800" channel="HOY資訊">
<title lang="zh">全運倒數</title>
<desc lang="zh"> </desc>
</programme>
<programme start="20251023080000 +0800" stop="20251023083000 +0800" channel="HOY資訊">
<title lang="zh">Cable 早晨</title>
<desc lang="zh"> </desc>
</programme>
<programme start="20251023083000 +0800" stop="20251023085800 +0800" channel="HOY資訊">
<title lang="zh">Cable 早晨</title>
<desc lang="zh"> </desc>
</programme>
<programme start="20251023085800 +0800" stop="20251023090000 +0800" channel="HOY資訊">
<title lang="zh">全運倒數</title>
<desc lang="zh"> </desc>
</programme>
<programme start="20251023090000 +0800" stop="20251023100000 +0800" channel="HOY資訊">
<title lang="zh">股市直播室</title>
<desc lang="zh"> </desc>
</programme>
<programme start="20251023100000 +0800" stop="20251023102500 +0800" channel="HOY資訊">
<title lang="zh">有線新聞</title>
<desc lang="zh"> </desc>
</programme>
<programme start="20251023102500 +0800" stop="20251023103000 +0800" channel="HOY資訊">
<title lang="zh">House730 特約 : 樓市導航</title>
<desc lang="zh"> </desc>
</programme>
<programme start="20251023103000 +0800" stop="20251023110000 +0800" channel="HOY資訊">
<title lang="zh">政經CHAT</title>
<desc lang="zh"> </desc>
</programme>
<programme start="20251023110000 +0800" stop="20251023112500 +0800" channel="HOY資訊">
<title lang="zh">有線新聞</title>
<desc lang="zh"> </desc>
</programme>
<programme start="20251023112500 +0800" stop="20251023113000 +0800" channel="HOY資訊">
<title lang="zh">House730 特約 : 樓市導航</title>
<desc lang="zh"> </desc>
</programme>
<programme start="20251023113000 +0800" stop="20251023120000 +0800" channel="HOY資訊">
<title lang="zh">28Hse特約：家家有求</title>
<desc lang="zh"> </desc>
</programme>
<programme start="20251023120000 +0800" stop="20251023122500 +0800" channel="HOY資訊">
<title lang="zh">有線新聞</title>
<desc lang="zh"> </desc>
</programme>
<programme start="20251023122500 +0800" stop="20251023123000 +0800" channel="HOY資訊">
<title lang="zh">防災應急18識</title>
<desc lang="zh"> </desc>
</programme>
<programme start="20251023123000 +0800" stop="20251023130000 +0800" channel="HOY資訊">
<title lang="zh">午間新聞</title>
<desc lang="zh"> </desc>
</programme>
<programme start="20251023130000 +0800" stop="20251023132800 +0800" channel="HOY資訊">
<title lang="zh">有線新聞</title>
<desc lang="zh"> </desc>
</programme>
<programme start="20251023132800 +0800" stop="20251023133000 +0800" channel="HOY資訊">
<title lang="zh">全運倒數</title>
<desc lang="zh"> </desc>
</programme>
<programme start="20251023133000 +0800" stop="20251023140000 +0800" channel="HOY資訊">
<title lang="zh">家國天下</title>
<desc lang="zh"> </desc>
</programme>
<programme start="20251023140000 +0800" stop="20251023142800 +0800" channel="HOY資訊">
<title lang="zh">有線新聞</title>
<desc lang="zh"> </desc>
</programme>
<programme start="20251023142800 +0800" stop="20251023143000 +0800" channel="HOY資訊">
<title lang="zh">全運倒數</title>
<desc lang="zh"> </desc>
</programme>
<programme start="20251023143000 +0800" stop="20251023150000 +0800" channel="HOY資訊">
<title lang="zh">有線新聞</title>
<desc lang="zh"> </desc>
</programme>
<programme start="20251023150000 +0800" stop="20251023152800 +0800" channel="HOY資訊">
<title lang="zh">有線新聞</title>
<desc lang="zh"> </desc>
</programme>
<programme start="20251023152800 +0800" stop="20251023153000 +0800" channel="HOY資訊">
<title lang="zh">全運倒數</title>
<desc lang="zh"> </desc>
</programme>
<programme start="20251023153000 +0800" stop="20251023160000 +0800" channel="HOY資訊">
<title lang="zh">有線新聞</title>
<desc lang="zh"> </desc>
</programme>
<programme start="20251023160000 +0800" stop="20251023163000 +0800" channel="HOY資訊">
<title lang="zh">股市直播室</title>
<desc lang="zh"> </desc>
</programme>
<programme start="20251023163000 +0800" stop="20251023170000 +0800" channel="HOY資訊">
<title lang="zh">有線新聞</title>
<desc lang="zh"> </desc>
</programme>
<programme start="20251023170000 +0800" stop="20251023173000 +0800" channel="HOY資訊">
<title lang="zh">有線新聞</title>
<desc lang="zh"> </desc>
</programme>
<programme start="20251023173000 +0800" stop="20251023175800 +0800" channel="HOY資訊">
<title lang="zh">股市直播室</title>
<desc lang="zh"> </desc>
</programme>
<programme start="20251023175800 +0800" stop="20251023180000 +0800" channel="HOY資訊">
<title lang="zh">全運倒數</title>
<desc lang="zh"> </desc>
</programme>
<programme start="20251023180000 +0800" stop="20251023183000 +0800" channel="HOY資訊">
<title lang="zh">手語新聞報道</title>
<desc lang="zh"> </desc>
</programme>
<programme start="20251023183000 +0800" stop="20251023184500 +0800" channel="HOY資訊">
<title lang="zh">六點半新聞報道</title>
<desc lang="zh"> </desc>
</programme>
<programme start="20251023184500 +0800" stop="20251023185500 +0800" channel="HOY資訊">
<title lang="zh">焦點財經</title>
<desc lang="zh"> </desc>
</programme>
<programme start="20251023185500 +0800" stop="20251023190000 +0800" channel="HOY資訊">
<title lang="zh">House730 特約 : 樓市導航</title>
<desc lang="zh"> </desc>
</programme>
<programme start="20251023190000 +0800" stop="20251023195000 +0800" channel="HOY資訊">
<title lang="zh">7點直播室</title>
<desc lang="zh"> </desc>
</programme>
<programme start="20251023195000 +0800" stop="20251023200000 +0800" channel="HOY資訊">
<title lang="zh">28Hse特約 : 每日樓市</title>
<desc lang="zh"> </desc>
</programme>
<programme start="20251023200000 +0800" stop="20251023203000 +0800" channel="HOY資訊">
<title lang="zh">國際最前線</title>
<desc lang="zh"> </desc>
</programme>
<programme start="20251023203000 +0800" stop="20251023205800 +0800" channel="HOY資訊">
<title lang="zh">一線搜查</title>
<desc lang="zh"> </desc>
</programme>
<programme start="20251023205800 +0800" stop="20251023210000 +0800" channel="HOY資訊">
<title lang="zh">全運倒數</title>
<desc lang="zh"> </desc>
</programme>
<programme start="20251023210000 +0800" stop="20251023214000 +0800" channel="HOY資訊">
<title lang="zh">晚間直播室</title>
<desc lang="zh"> </desc>
</programme>
<programme start="20251023214000 +0800" stop="20251023214500 +0800" channel="HOY資訊">
<title lang="zh">House730 特約 : 樓市導航</title>
<desc lang="zh"> </desc>
</programme>
<programme start="20251023214500 +0800" stop="20251023220000 +0800" channel="HOY資訊">
<title lang="zh">焦點財經及28Hse特約:每日樓市</title>
<desc lang="zh"> </desc>
</programme>
<programme start="20251023220000 +0800" stop="20251023223000 +0800" channel="HOY資訊">
<title lang="zh">智‧創未來</title>
<desc lang="zh"> </desc>
</programme>
<programme start="20251023223000 +0800" stop="20251023225800 +0800" channel="HOY資訊">
<title lang="zh">一線搜查</title>
<desc lang="zh"> </desc>
</programme>
<programme start="20251023225800 +0800" stop="20251023230000 +0800" channel="HOY資訊">
<title lang="zh">全運倒數</title>
<desc lang="zh"> </desc>
</programme>
<programme start="20251023230000 +0800" stop="20251023233000 +0800" channel="HOY資訊">
<title lang="zh">有線新聞</title>
<desc lang="zh"> </desc>
</programme>
<programme start="20251023233000 +0800" stop="20251024000000 +0800" channel="HOY資訊">
<title lang="zh">有線新聞</title>
<desc lang="zh"> </desc>
</programme>
</tv>
